{"algorithm_leetcode_1.md":"f11756b4","guide_migration-from-vitepress-0.md":"ea85bf17","guide_migration-from-vuepress.md":"b6b3feba","guide_theme-carbon-ads.md":"5902c5bb","guide_theme-badge.md":"e284b80c","config_introduction.md":"9eca5928","guide_getting-started.md":"487f6735","guide_frontmatter.md":"c0517e3f","config_app-configs.md":"c195830c","config_frontmatter-configs.md":"6e9083ce","config_theme-configs.md":"0caafd84","guide_api.md":"ef2d1fd9","guide_asset-handling.md":"29ab4001","guide_configuration.md":"4ea5fdf1","guide_deploying.md":"b9397151","guide_theme-search.md":"56d90c92","guide_theme-prev-next-link.md":"ba968914","guide_theme-edit-link.md":"86d6d320","guide_theme-last-updated.md":"17429d7e","guide_theme-layout.md":"ab5cf6d3","guide_theme-nav.md":"d7a64a55","note_error.md":"008e51d9","guide_theme-sidebar.md":"d349031b","guide_theme-team-page.md":"0fa3ba8f","getting-started.md":"35341f62","index.md":"cfcc7b54","guide_markdown.md":"7decab9f","algorithm_leetcode_index.md":"a801b915","guide_theme-home-page.md":"af6863af","guide_using-vue.md":"80c10da8","guide_theme-introduction.md":"31d2fb89","guide_theme-footer.md":"ca975d7b","guide_what-is-vitepress.md":"905e5372","note_error_git.md":"e39bb822","tools_cipher.md":"7fb95fec","note_posix-cron.md":"381f26ef","note_shell.md":"145b1382","note_vitepress.md":"ebc8566a","note_note.md":"ca5a3098","note_nodejs.md":"8517f87d","note_javascript-questions.md":"ad187afd","tools_emoji-list.md":"cb941f7e","tools_javascript-regular.md":"0dd93b74","tools_javascript-function.md":"510ff911"}
